{
    "matrices": [
        {
            "matrix": [
                [0.0, 0.0, 0.0, 1.0],
                [8000.0, 400.0, 20.0, 1.0],
                [125000.0, 2500.0, 50.0, 1.0],
                [1000000.0, 10000.0, 100.0, 1.0]
            ],
            "determinant": 12000000000.0
        },
        {
            "matrix": [
                [50.0, 0.0, 0.0, 1.0],
                [100.0, 400.0, 20.0, 1.0],
                [130.0, 2500.0, 50.0, 1.0],
                [210.0, 10000.0, 100.0, 1.0]
            ],
            "determinant": 4500000.0
        },
        {
            "matrix": [
                [0.0, 50.0, 0.0, 1.0],
                [8000.0, 100.0, 20.0, 1.0],
                [125000.0, 130.0, 50.0, 1.0],
                [1000000.0, 210.0, 100.0, 1.0]
            ],
            "determinant": -675000000.0
        },
        {
            "matrix": [
                [0.0, 0.0, 50.0, 1.0],
                [8000.0, 400.0, 100.0, 1.0],
                [125000.0, 2500.0, 130.0, 1.0],
                [1000000.0, 10000.0, 210.0, 1.0]
            ],
            "determinant": 41700000000.0
        },
        {
            "matrix": [
                [0.0, 0.0, 0.0, 50.0],
                [8000.0, 400.0, 20.0, 100.0],
                [125000.0, 2500.0, 50.0, 130.0],
                [1000000.0, 10000.0, 100.0, 210.0]
            ],
            "determinant": 600000000000.0
        }
    ],
    "solutions": [0.000375, -0.05625, 3.475, 50.0]
}
